documentacion/segmentos.v
module segmentos(
    input [3:0] bin,
    output reg [6:0] seg
);

always @(*) begin
    case(bin)
        4'd0: seg = 7'b1000000;
        4'd1: seg = 7'b1111001;
        4'd2: seg = 7'b0100100;
        4'd3: seg = 7'b0110000;
        4'd4: seg = 7'b0011001;
        4'd5: seg = 7'b0010010;
        4'd6: seg = 7'b0000010;
        4'd7: seg = 7'b1111000;
        4'd8: seg = 7'b0000000;
        4'd9: seg = 7'b0010000;

        
        default: seg = 7'b1111111;
    endcase
end
endmodule

documentacion/segmentos7_tb.v
`timescale 1ns/1ps

module tb_segmentos;

reg [3:0] bin;
wire [6:0] seg;

integer i;


segmentos UUT(
    .bin(bin),
    .seg(seg)
);

initial begin
    $dumpfile("segmentos_tb.vcd");
    $dumpvars(0, tb_segmentos);

    
    for (i = 0; i < 16; i = i + 1) begin
        bin = i;
        #10;
    end

    $finish;
end

endmodule

documentacion/segmentos_tb.vcd
$date
	Thu Apr 02 22:48:24 2026
$end
$version
	Icarus Verilog
$end
$timescale
	1ps
$end
$scope module tb_segmentos $end
$var wire 7 ! seg [6:0] $end
$var reg 4 " bin [3:0] $end
$var integer 32 # i [31:0] $end
$scope module UUT $end
$var wire 4 $ bin [3:0] $end
$var reg 7 % seg [6:0] $end
$upscope $end
$upscope $end
$enddefinitions $end
#0
$dumpvars
b1000000 %
b0 $
b0 #
b0 "
b1000000 !
$end
#10000
b1111001 !
b1111001 %
b1 "
b1 $
b1 #
#20000
b100100 !
b100100 %
b10 "
b10 $
b10 #
#30000
b110000 !
b110000 %
b11 "
b11 $
b11 #
#40000
b11001 !
b11001 %
b100 "
b100 $
b100 #
#50000
b10010 !
b10010 %
b101 "
b101 $
b101 #
#60000
b10 !
b10 %
b110 "
b110 $
b110 #
#70000
b1111000 !
b1111000 %
b111 "
b111 $
b111 #
#80000
b0 !
b0 %
b1000 "
b1000 $
b1000 #
#90000
b10000 !
b10000 %
b1001 "
b1001 $
b1001 #
#100000
b1111111 !
b1111111 %
b1010 "
b1010 $
b1010 #
#110000
b1011 "
b1011 $
b1011 #
#120000
b1100 "
b1100 $
b1100 #
#130000
b1101 "
b1101 $
b1101 #
#140000
b1110 "
b1110 $
b1110 #
#150000
b1111 "
b1111 $
b1111 #
#160000
b10000 #
